{
    "Ax": {
        "error": 2.0485926539836534e-07,
        "error_type": "SEM",
        "filter_outliers_dict": {
            "filter_outliers": false,
            "iterations": 1,
            "std_devs": 2
        },
        "fit": "average",
        "value": -0.00020228292131402694
    },
    "H2": {
        "error": 1.484609109291521e-07,
        "error_type": "SEM",
        "filter_outliers_dict": {
            "filter_outliers": true,
            "iterations": 1,
            "std_devs": 2
        },
        "fit": "average",
        "value": -0.0002839101274264281
    },
    "H4": {
        "error": 1.6447495368730155e-07,
        "error_type": "SEM",
        "filter_outliers_dict": {
            "filter_outliers": true,
            "iterations": 1,
            "std_devs": 2
        },
        "fit": "average",
        "value": -7.790800957142856e-05
    },
    "L2": {
        "error": 1.4086682524058958e-07,
        "error_type": "SEM",
        "filter_outliers_dict": {
            "filter_outliers": true,
            "iterations": 1,
            "std_devs": 2
        },
        "fit": "average",
        "value": -2.3446939765511153e-05
    },
    "L4": {
        "error": 1.7039058128773107e-10,
        "error_type": "SEM",
        "filter_outliers_dict": {
            "filter_outliers": false,
            "iterations": 1,
            "std_devs": 2
        },
        "fit": "average",
        "value": 4.2666666666666674e-10
    }
}